README.md
setup.py
mc_uncertainty/__init__.py
mc_uncertainty/lib.py
mc_uncertainty.egg-info/PKG-INFO
mc_uncertainty.egg-info/SOURCES.txt
mc_uncertainty.egg-info/dependency_links.txt
mc_uncertainty.egg-info/requires.txt
mc_uncertainty.egg-info/top_level.txt