Metadata-Version: 2.1
Name: mc-uncertainty
Version: 0.1.2
Summary: Calculate uncertainty measures from Monte Carlo sampled model outputs.
Home-page: https://github.com/tayden/mc-uncertainty
Author: Taylor Denouden
Author-email: taylordenouden@gmail.com
License: MIT
Platform: UNKNOWN
